NiaogeDeLinuxSifangCaiFuwuqiJiashePianDisanban/README.md
NiaogeDeLinuxSifangCaiFuwuqiJiashePianDisanban/__init__.py
NiaogeDeLinuxSifangCaiFuwuqiJiashePianDisanban/__main__.py
NiaogeDeLinuxSifangCaiFuwuqiJiashePianDisanban/file.epub
NiaogeDeLinuxSifangCaiFuwuqiJiashePianDisanban/index.html
NiaogeDeLinuxSifangCaiFuwuqiJiashePianDisanban/css/__init__.py
NiaogeDeLinuxSifangCaiFuwuqiJiashePianDisanban/css/annotations.css
NiaogeDeLinuxSifangCaiFuwuqiJiashePianDisanban/css/main.css
NiaogeDeLinuxSifangCaiFuwuqiJiashePianDisanban/css/normalize.css
NiaogeDeLinuxSifangCaiFuwuqiJiashePianDisanban/css/popup.css
NiaogeDeLinuxSifangCaiFuwuqiJiashePianDisanban/font/__init__.py
NiaogeDeLinuxSifangCaiFuwuqiJiashePianDisanban/font/fontello.eot
NiaogeDeLinuxSifangCaiFuwuqiJiashePianDisanban/font/fontello.svg
NiaogeDeLinuxSifangCaiFuwuqiJiashePianDisanban/font/fontello.ttf
NiaogeDeLinuxSifangCaiFuwuqiJiashePianDisanban/font/fontello.woff
NiaogeDeLinuxSifangCaiFuwuqiJiashePianDisanban/img/__init__.py
NiaogeDeLinuxSifangCaiFuwuqiJiashePianDisanban/img/annotator-glyph-sprite.png
NiaogeDeLinuxSifangCaiFuwuqiJiashePianDisanban/img/annotator-icon-sprite.png
NiaogeDeLinuxSifangCaiFuwuqiJiashePianDisanban/img/apple-touch-icon.png
NiaogeDeLinuxSifangCaiFuwuqiJiashePianDisanban/img/cancelfullscreen.png
NiaogeDeLinuxSifangCaiFuwuqiJiashePianDisanban/img/close.png
NiaogeDeLinuxSifangCaiFuwuqiJiashePianDisanban/img/fullscreen.png
NiaogeDeLinuxSifangCaiFuwuqiJiashePianDisanban/img/loader.gif
NiaogeDeLinuxSifangCaiFuwuqiJiashePianDisanban/img/menu-icon.png
NiaogeDeLinuxSifangCaiFuwuqiJiashePianDisanban/img/save.png
NiaogeDeLinuxSifangCaiFuwuqiJiashePianDisanban/img/saved.png
NiaogeDeLinuxSifangCaiFuwuqiJiashePianDisanban/img/settings-s.png
NiaogeDeLinuxSifangCaiFuwuqiJiashePianDisanban/img/settings.png
NiaogeDeLinuxSifangCaiFuwuqiJiashePianDisanban/img/star.png
NiaogeDeLinuxSifangCaiFuwuqiJiashePianDisanban/js/__init__.py
NiaogeDeLinuxSifangCaiFuwuqiJiashePianDisanban/js/epub.js
niaoge_de_linux_sifang_cai_fuwuqi_jiashe_pian_disanban-2024.3.1.0.dist-info/METADATA
niaoge_de_linux_sifang_cai_fuwuqi_jiashe_pian_disanban-2024.3.1.0.dist-info/WHEEL
niaoge_de_linux_sifang_cai_fuwuqi_jiashe_pian_disanban-2024.3.1.0.dist-info/entry_points.txt
niaoge_de_linux_sifang_cai_fuwuqi_jiashe_pian_disanban-2024.3.1.0.dist-info/top_level.txt
niaoge_de_linux_sifang_cai_fuwuqi_jiashe_pian_disanban-2024.3.1.0.dist-info/RECORD
